setup.py
LineageTracker/ClassifyHaplogroup.py
LineageTracker/ClusterHaplogroup.py
LineageTracker/CommonAncestor.py
LineageTracker/Config.ini
LineageTracker/EstimateTime.py
LineageTracker/FilesIO.py
LineageTracker/GenotypeSTR.py
LineageTracker/GetConfig.py
LineageTracker/HaploNetwork.py
LineageTracker/PhyloHaplogroup.py
LineageTracker/RunLineagerTracker.py
LineageTracker/StatisticsAnalysis.py
LineageTracker/__init__.py
LineageTracker/Data/HaplogroupInfo.csv
LineageTracker/Data/ISOGG_haplogroup_info.csv
LineageTracker/Data/ISOGG_population_index.csv
LineageTracker/Data/Y_STR.refinfo
LineageTracker/Data/Y_STR_panel.csv
LineageTracker/Data/Y_STR_precidtion_panel.csv
LineageTracker/Data/Y_chromosome_region.bed
LineageTracker/Data/base_tree.nw
LineageTracker/Data/haplogroup_calibration.csv
LineageTracker/Data/haplogroup_tree_2018.txt
LineageTracker/GetLineage/MatchVariant.py
LineageTracker/GetLineage/TrackLineage.py
LineageTracker/GetLineage/__init__.py
LineageTracker/ProcessData/ConvertData.py
LineageTracker/ProcessData/ReadFilterData.py
LineageTracker/ProcessData/__init__.py
LineageTracker/Test/TestProgram.py
LineageTracker/Test/__init__.py
LineageTracker/Test/TestData/KGP_O2_sample7.matrix
LineageTracker/Test/TestData/KGP_hgs.hg
LineageTracker/Test/TestData/KGP_pops.pop
LineageTracker/Test/TestData/KGP_sample7.net
LineageTracker/Test/TestData/KGP_sample7.tree.nwk
LineageTracker/Test/TestData/KGP_sample7.vcf
LineageTracker/sans-serif/Arial.ttf
LineageTracker/src/Makefile
LineageTracker/src/mcmctree.c
LineageTracker/src/paml.h
LineageTracker/src/tools.c
LineageTracker/src/treespace.c
LineageTracker/src/treesub.c
Y_LineageTracker.egg-info/PKG-INFO
Y_LineageTracker.egg-info/SOURCES.txt
Y_LineageTracker.egg-info/dependency_links.txt
Y_LineageTracker.egg-info/entry_points.txt
Y_LineageTracker.egg-info/not-zip-safe
Y_LineageTracker.egg-info/requires.txt
Y_LineageTracker.egg-info/top_level.txt