Metadata-Version: 1.2
Name: Y-LineageTracker
Version: 1.3.0
Summary: Y-LineageTracker: A framework to fully analyze human Y-chromosome sequencing data
Home-page: http://www.picb.ac.cn/PGG/resource.php
Author: Hao Chen
Author-email: chenhao@picb.ac.cn
License: GPL-3.0
Keywords: Bioinformatics,Computational biology,Population genetics,Genomics,Y chromosome,haplogroup,Y-STR
Platform: UNKNOWN
Classifier: Development Status :: 3 - Alpha
Classifier: License :: OSI Approved :: GNU General Public License v3 (GPLv3)
Classifier: Intended Audience :: Developers
Classifier: Intended Audience :: Science/Research
Classifier: Programming Language :: Python :: 3
Classifier: Programming Language :: Python :: 3.6
Classifier: Programming Language :: C
Classifier: Topic :: Scientific/Engineering :: Bio-Informatics
Classifier: Topic :: Scientific/Engineering :: Visualization
Requires-Python: >=3.6
